Workbook

Sheet README
A1: Jade AI unit-economics scenario model
A2: Companion to ECONOMICS.md in github.com/vyshnavtammanaboina/wearable-ai-audit. Every figure is an estimate
A3: under stated assumptions; Ultrahuman publishes no segment data for Jade. The model exists to test whether
A4: the verdict survives the ranges, not to defend any midpoint.
A6: HOW TO USE
A7: Edit only blue-font cells on the Inputs sheet. Yellow-filled cells are the three main levers:
A8: 1) Inference scenario (1=Frontier API, 2=Mid-tier API, 3=Self-hosted small model)
A9: 2) Paid-user queries per month (the heavy-user lever)
A10: 3) Paid conversion rate
A11: Model sheet computes both architectures side by side. Sensitivity sheet shows where each one breaks.
A13: THE CORE MECHANIC
A14: On-demand: every question fires a 10-15 call multi-agent synthesis, so COGS scales with questions asked.
... A23: User base, conversion, query volumes: author estimates. Flagged blue; every one is a lever.

Sheet Inputs
A1: COMPANY BASE (reported / trade press)
A2: FY25 revenue ($mm) | B2: 68
A3: FY25 net profit ($mm) | B3: 8.8
A4: Annualised run rate ($mm) | B4: 150
A6: USERS & PRICING (author estimates - levers)
A7: Cumulative active ring base (users) | B7: 400000
A8: Regular free-tier Jade users | B8: 60000
A9: Paid conversion of active base | B9: 0.05
A10: Jade Pro price ($/user/month) | B10: 3.99
A12: USAGE (author estimates - levers)
A13: Paid-user questions per month | B13: 60
A14: Free-user questions per month | B14: 15
A16: INFERENCE COST PER ON-DEMAND QUERY ($)
A17: Scenario 1: Frontier API | B17: 0.35
A18: Scenario 2: Mid-tier API | B18: 0.035
A19: Scenario 3: Self-hosted small model | B19: 0.006
A20: SELECTED SCENARIO (1, 2 or 3) | B20: 1
A22: PRECOMPUTE ARCHITECTURE
A23: Digests per user per year | B23: 52
A24: Digest generation cost (x one on-demand query) | B24: 1
A25: Follow-up question cost ($) | B25: 0.015

Sheet Model
A1: SELECTED SCENARIO
A2: Inference scenario | B2: =INDEX({"Frontier API","Mid-tier API","Self-hosted SLM"},Inputs!B20)
A3: Cost per on-demand query | B3: =INDEX(Inputs!B17:B19,Inputs!B20)
A4: Digest generation cost | B4: =B3*Inputs!B24
A6: PER PAID USER, MONTHLY
B7: On-demand | C7: Precompute
A8: Revenue | B8: =Inputs!B10 | C8: =Inputs!B10
A9: COGS | B9: =Inputs!B13*B3 | C9: =(Inputs!B23/12)*$B$4+Inputs!B13*Inputs!B25
A10: Gross margin ($) | B10: =B8-B9 | C10: =C8-C9
A11: Gross margin (%) | B11: =IF(B8=0,0,B10/B8) | C11: =IF(C8=0,0,C10/C8)
A13: PER FREE USER, MONTHLY
A14: COGS | B14: =Inputs!B14*B3 | C14: =(Inputs!B23/12)*$B$4+Inputs!B14*Inputs!B25
A16: COHORT, ANNUAL ($)
A17: Paid subscribers | B17: =Inputs!B7*Inputs!B9
A18: Paid revenue / yr | B18: =B17*Inputs!B10*12
A19: Paid COGS / yr | B19: =B17*B9*12 | C19: =B17*C9*12
A20: Paid gross margin / yr | B20: =B18-B19 | C20: =B18-C19
A21: Free-tier cost / yr | B21: =Inputs!B8*B14*12 | C21: =Inputs!B8*C14*12
A22: Total AI line, net / yr | B22: =B20-B21 | C22: =C20-C21
A24: CONTEXT
A25: Paid revenue as % of run rate | B25: =B18/(Inputs!B4*1000000)
A26: Free-tier cost as % of FY25 net profit | B26: =B21/(Inputs!B3*1000000) | C26: =C21/(Inputs!B3*1000000)

Sheet Sensitivity
A1: PAID GROSS MARGIN % vs QUESTIONS PER MONTH (selected scenario)
A2: Questions / month | B2: 15 | C2: 30 | D2: 60 | E2: 120 | F2: 240
A3: On-demand | B3: =(Inputs!$B$10-B$2*Model!$B$3)/Inputs!$B$10 | C3: =(Inputs!$B$10-C$2*Model!$B$3)/Inputs!$B$10 | D3: =(Inputs!$B$10-D$2*Model!$B$3)/Inputs!$B$10 | E3: =(Inputs!$B$10-E$2*Model!$B$3)/Inputs!$B$10 | F3: =(Inputs!$B$10-F$2*Model!$B$3)/Inputs!$B$10
A4: Precompute | B4: =(Inputs!$B$10-((Inputs!$B$23/12)*Model!$B$4+B$2*Inputs!$B$25))/Inputs!$B$10 | C4: =(Inputs!$B$10-((Inputs!$B$23/12)*Model!$B$4+C$2*Inputs!$B$25))/Inputs!$B$10 | D4: =(Inputs!$B$10-((Inputs!$B$23/12)*Model!$B$4+D$2*Inputs!$B$25))/Inputs!$B$10 | E4: =(Inputs!$B$10-((Inputs!$B$23/12)*Model!$B$4+E$2*Inputs!$B$25))/Inputs!$B$10 | F4: =(Inputs!$B$10-((Inputs!$B$23/12)*Model!$B$4+F$2*Inputs!$B$25))/Inputs!$B$10
A5: On-demand margin collapses with usage; precompute is nearly flat. That difference is the whole argument.
A7: PRECOMPUTE: ANNUAL AI LINE NET ($) vs CONVERSION x PRICE
A8: Conversion \ Price ($/mo) | B8: 1.99 | C8: 3.99 | D8: 5.99 | E8: 7.99
A9: 0.02 | B9: =Inputs!$B$7*$A9*(B$8-((Inputs!$B$23/12)*Model!$B$4+Inputs!$B$13*Inputs!$B$25))*12-Inputs!$B$8*Model!$C$14*12 | C9: =Inputs!$B$7*$A9*(C$8-((Inputs!$B$23/12)*Model!$B$4+Inputs!$B$13*Inputs!$B$25))*12-Inputs!$B$8*Model!$C$14*12 | D9: =Inputs!$B$7*$A9*(D$8-((Inputs!$B$23/12)*Model!$B$4+Inputs!$B$13*Inputs!$B$25))*12-Inputs!$B$8*Model!$C$14*12 | E9: =Inputs!$B$7*$A9*(E$8-((Inputs!$B$23/12)*Model!$B$4+Inputs!$B$13*Inputs!$B$25))*12-Inputs!$B$8*Model!$C$14*12
A10: 0.05 | B10: =Inputs!$B$7*$A10*(B$8-((Inputs!$B$23/12)*Model!$B$4+Inputs!$B$13*Inputs!$B$25))*12-Inputs!$B$8*Model!$C$14*12 | C10: =Inputs!$B$7*$A10*(C$8-((Inputs!$B$23/12)*Model!$B$4+Inputs!$B$13*Inputs!$B$25))*12-Inputs!$B$8*Model!$C$14*12 | D10: =Inputs!$B$7*$A10*(D$8-((Inputs!$B$23/12)*Model!$B$4+Inputs!$B$13*Inputs!$B$25))*12-Inputs!$B$8*Model!$C$14*12 | E10: =Inputs!$B$7*$A10*(E$8-((Inputs!$B$23/12)*Model!$B$4+Inputs!$B$13*Inputs!$B$25))*12-Inputs!$B$8*Model!$C$14*12
A11: 0.1 | B11: =Inputs!$B$7*$A11*(B$8-((Inputs!$B$23/12)*Model!$B$4+Inputs!$B$13*Inputs!$B$25))*12-Inputs!$B$8*Model!$C$14*12 | C11: =Inputs!$B$7*$A11*(C$8-((Inputs!$B$23/12)*Model!$B$4+Inputs!$B$13*Inputs!$B$25))*12-Inputs!$B$8*Model!$C$14*12 | D11: =Inputs!$B$7*$A11*(D$8-((Inputs!$B$23/12)*Model!$B$4+Inputs!$B$13*Inputs!$B$25))*12-Inputs!$B$8*Model!$C$14*12 | E11: =Inputs!$B$7*$A11*(E$8-((Inputs!$B$23/12)*Model!$B$4+Inputs!$B$13*Inputs!$B$25))*12-Inputs!$B$8*Model!$C$14*12
A12: 0.15 | B12: =Inputs!$B$7*$A12*(B$8-((Inputs!$B$23/12)*Model!$B$4+Inputs!$B$13*Inputs!$B$25))*12-Inputs!$B$8*Model!$C$14*12 | C12: =Inputs!$B$7*$A12*(C$8-((Inputs!$B$23/12)*Model!$B$4+Inputs!$B$13*Inputs!$B$25))*12-Inputs!$B$8*Model!$C$14*12 | D12: =Inputs!$B$7*$A12*(D$8-((Inputs!$B$23/12)*Model!$B$4+Inputs!$B$13*Inputs!$B$25))*12-Inputs!$B$8*Model!$C$14*12 | E12: =Inputs!$B$7*$A12*(E$8-((Inputs!$B$23/12)*Model!$B$4+Inputs!$B$13*Inputs!$B$25))*12-Inputs!$B$8*Model!$C$14*12
A13: Paid margin at cohort scale minus free-tier cost, precompute architecture, selected scenario.
